{
    "cars": [{
            "id": 3,
            "name": "Skoda",
            "category": "cars",
            "article": "https://ru.motor1.com/news/571185/skoda-stop-production/",
            "logo": "https://w7.pngwing.com/pngs/273/475/png-transparent-%C5%A0koda-auto-car-%C5%A0koda-superb-%C5%A0koda-vision-x-skoda-text-logo-car.png",
            "date": "2022-03-03T00:00:00.000Z"
        },
        {
            "id": 4,
            "name": "Jaguar Land Rover",
            "category": "cars",
            "article": "https://autoreview.ru/news/kompaniya-jaguar-land-rover-ostanovila-postavki-avtomobiley-v-rossiyu",
            "logo": "https://w7.pngwing.com/pngs/62/850/png-transparent-jaguar-land-rover-jaguar-cars-land-rover-emblem-label-text.png",
            "date": "2022-02-25T00:00:00.000Z"
        },
        {
            "id": 5,
            "name": "Volvo",
            "category": "cars",
            "article": "https://motor.ru/news/russian-cars-market-01-03-2022.htm",
            "logo": "https://pngimg.com/uploads/volvo/volvo_PNG64.png",
            "date": "2022-03-01T00:00:00.000Z"
        }
    ]
}